{
    "min": "5.64670000",
    "max": "8.64800000",
    "count": 42579,
    "step": 0.046506666666666634,
    "data": [
        {
            "min": 5.758846666666665,
            "max": 5.805353333333332,
            "count": 61,
            "lastTime": 1561708681192
        },
        {
            "min": 5.805353333333332,
            "max": 5.8518599999999985,
            "count": 106,
            "lastTime": 1561709700592
        },
        {
            "min": 5.8518599999999985,
            "max": 5.898366666666665,
            "count": 87,
            "lastTime": 1561709760634
        },
        {
            "min": 5.898366666666665,
            "max": 5.944873333333332,
            "count": 23,
            "lastTime": 1561709940974
        },
        {
            "min": 5.944873333333332,
            "max": 5.991379999999999,
            "count": 38,
            "lastTime": 1561710180882
        },
        {
            "min": 5.991379999999999,
            "max": 6.037886666666665,
            "count": 115,
            "lastTime": 1561719060627
        },
        {
            "min": 6.037886666666665,
            "max": 6.084393333333332,
            "count": 135,
            "lastTime": 1561721281128
        },
        {
            "min": 6.084393333333332,
            "max": 6.130899999999999,
            "count": 36,
            "lastTime": 1561716360948
        },
        {
            "min": 6.130899999999999,
            "max": 6.177406666666665,
            "count": 0,
            "lastTime": 1561713721005
        },
        {
            "min": 6.177406666666665,
            "max": 6.223913333333332,
            "count": 0
        },
        {
            "min": 6.223913333333332,
            "max": 6.270419999999999,
            "count": 0
        },
        {
            "min": 6.270419999999999,
            "max": 6.3169266666666655,
            "count": 0,
            "lastTime": 1561651740774
        },
        {
            "min": 6.3169266666666655,
            "max": 6.363433333333332,
            "count": 85,
            "lastTime": 1561651680626
        },
        {
            "min": 6.363433333333332,
            "max": 6.409939999999999,
            "count": 343,
            "lastTime": 1561651500955
        },
        {
            "min": 6.409939999999999,
            "max": 6.456446666666666,
            "count": 73,
            "lastTime": 1561647600757
        },
        {
            "min": 6.456446666666666,
            "max": 6.502953333333332,
            "count": 1,
            "lastTime": 1561637160755
        },
        {
            "min": 6.502953333333332,
            "max": 6.549459999999999,
            "count": 0,
            "lastTime": 1561622160637
        },
        {
            "min": 6.549459999999999,
            "max": 6.595966666666666,
            "count": 0,
            "lastTime": 1561618980477
        },
        {
            "min": 6.595966666666666,
            "max": 6.642473333333332,
            "count": 0,
            "lastTime": 1561616700898
        },
        {
            "min": 6.642473333333332,
            "max": 6.688979999999999,
            "count": 14,
            "lastTime": 1561616280589
        },
        {
            "min": 6.688979999999999,
            "max": 6.735486666666666,
            "count": 79,
            "lastTime": 1561615440649
        },
        {
            "min": 6.735486666666666,
            "max": 6.781993333333332,
            "count": 14,
            "lastTime": 1561610400618
        },
        {
            "min": 6.781993333333332,
            "max": 6.828499999999999,
            "count": 0,
            "lastTime": 1561608360484
        },
        {
            "min": 6.828499999999999,
            "max": 6.875006666666666,
            "count": 0,
            "lastTime": 1561594620958
        },
        {
            "min": 6.875006666666666,
            "max": 6.9215133333333325,
            "count": 0,
            "lastTime": 1561132801083
        },
        {
            "min": 6.9215133333333325,
            "max": 6.968019999999999,
            "count": 0,
            "lastTime": 1561163160429
        },
        {
            "min": 6.968019999999999,
            "max": 7.014526666666666,
            "count": 432,
            "lastTime": 1561493580759
        },
        {
            "min": 7.014526666666666,
            "max": 7.061033333333333,
            "count": 477,
            "lastTime": 1561581660460
        },
        {
            "min": 7.061033333333333,
            "max": 7.107539999999999,
            "count": 0,
            "lastTime": 1561527180375
        },
        {
            "min": 7.107539999999999,
            "max": 7.154046666666666,
            "count": 64,
            "lastTime": 1561581600580
        },
        {
            "min": 7.154046666666666,
            "max": 7.200553333333333,
            "count": 700,
            "lastTime": 1561581540856
        },
        {
            "min": 7.200553333333333,
            "max": 7.247059999999999,
            "count": 555,
            "lastTime": 1561581420476
        },
        {
            "min": 7.247059999999999,
            "max": 7.293566666666666,
            "count": 438,
            "lastTime": 1561569240836
        },
        {
            "min": 7.293566666666666,
            "max": 7.340073333333333,
            "count": 68,
            "lastTime": 1561581300540
        },
        {
            "min": 7.340073333333333,
            "max": 7.3865799999999995,
            "count": 375,
            "lastTime": 1561581240602
        }
    ]
}