{
    "min": "0.37000000",
    "max": "0.50823000",
    "count": 42575,
    "step": 0.0023726666666666675,
    "data": [
        {
            "min": 0.4034113333333332,
            "max": 0.40578399999999987,
            "count": 3,
            "lastTime": 1561670040779
        },
        {
            "min": 0.40578399999999987,
            "max": 0.40815666666666656,
            "count": 62,
            "lastTime": 1561708560530
        },
        {
            "min": 0.40815666666666656,
            "max": 0.41052933333333325,
            "count": 105,
            "lastTime": 1561710120600
        },
        {
            "min": 0.41052933333333325,
            "max": 0.41290199999999994,
            "count": 111,
            "lastTime": 1561710240545
        },
        {
            "min": 0.41290199999999994,
            "max": 0.4152746666666666,
            "count": 163,
            "lastTime": 1561721280871
        },
        {
            "min": 0.4152746666666666,
            "max": 0.4176473333333333,
            "count": 156,
            "lastTime": 1561720440989
        },
        {
            "min": 0.4176473333333333,
            "max": 0.42002,
            "count": 44,
            "lastTime": 1561716480953
        },
        {
            "min": 0.42002,
            "max": 0.4223926666666667,
            "count": 0,
            "lastTime": 1561711800892
        },
        {
            "min": 0.4223926666666667,
            "max": 0.4247653333333334,
            "count": 0,
            "lastTime": 1561651920502
        },
        {
            "min": 0.4247653333333334,
            "max": 0.4271380000000001,
            "count": 43,
            "lastTime": 1561651860998
        },
        {
            "min": 0.4271380000000001,
            "max": 0.42951066666666676,
            "count": 599,
            "lastTime": 1561651680529
        },
        {
            "min": 0.42951066666666676,
            "max": 0.43188333333333345,
            "count": 470,
            "lastTime": 1561651500938
        },
        {
            "min": 0.43188333333333345,
            "max": 0.43425600000000014,
            "count": 44,
            "lastTime": 1561637220609
        },
        {
            "min": 0.43425600000000014,
            "max": 0.43662866666666683,
            "count": 0,
            "lastTime": 1561624920502
        },
        {
            "min": 0.43662866666666683,
            "max": 0.4390013333333335,
            "count": 0,
            "lastTime": 1561622460594
        },
        {
            "min": 0.4390013333333335,
            "max": 0.4413740000000002,
            "count": 0,
            "lastTime": 1561163700474
        },
        {
            "min": 0.4413740000000002,
            "max": 0.4437466666666669,
            "count": 0,
            "lastTime": 1561165740582
        },
        {
            "min": 0.4437466666666669,
            "max": 0.4461193333333336,
            "count": 0,
            "lastTime": 1561165860410
        },
        {
            "min": 0.4461193333333336,
            "max": 0.4484920000000003,
            "count": 0,
            "lastTime": 1561616940627
        },
        {
            "min": 0.4484920000000003,
            "max": 0.45086466666666697,
            "count": 0,
            "lastTime": 1561178880763
        },
        {
            "min": 0.45086466666666697,
            "max": 0.45323733333333366,
            "count": 0,
            "lastTime": 1561616880480
        },
        {
            "min": 0.45323733333333366,
            "max": 0.45561000000000035,
            "count": 0,
            "lastTime": 1561616820555
        },
        {
            "min": 0.45561000000000035,
            "max": 0.45798266666666704,
            "count": 0,
            "lastTime": 1561616700514
        },
        {
            "min": 0.45798266666666704,
            "max": 0.4603553333333337,
            "count": 98,
            "lastTime": 1561616280565
        },
        {
            "min": 0.4603553333333337,
            "max": 0.4627280000000004,
            "count": 264,
            "lastTime": 1561615680939
        },
        {
            "min": 0.4627280000000004,
            "max": 0.4651006666666671,
            "count": 564,
            "lastTime": 1561615140765
        },
        {
            "min": 0.4651006666666671,
            "max": 0.4674733333333338,
            "count": 354,
            "lastTime": 1561611420472
        },
        {
            "min": 0.4674733333333338,
            "max": 0.4698460000000005,
            "count": 264,
            "lastTime": 1561607581156
        },
        {
            "min": 0.4698460000000005,
            "max": 0.4722186666666672,
            "count": 323,
            "lastTime": 1561596420672
        },
        {
            "min": 0.4722186666666672,
            "max": 0.47459133333333386,
            "count": 333,
            "lastTime": 1561583100472
        },
        {
            "min": 0.47459133333333386,
            "max": 0.47696400000000055,
            "count": 0,
            "lastTime": 1561582740440
        },
        {
            "min": 0.47696400000000055,
            "max": 0.47933666666666724,
            "count": 112,
            "lastTime": 1561582801065
        },
        {
            "min": 0.47933666666666724,
            "max": 0.48170933333333393,
            "count": 88,
            "lastTime": 1561581480864
        },
        {
            "min": 0.48170933333333393,
            "max": 0.4840820000000006,
            "count": 0,
            "lastTime": 1561580040898
        },
        {
            "min": 0.4840820000000006,
            "max": 0.4864546666666673,
            "count": 62,
            "lastTime": 1561581300514
        },
        {
            "min": 0.4864546666666673,
            "max": 0.488827333333334,
            "count": 39,
            "lastTime": 1561581240471
        }
    ]
}